swmjupyter/__init__.py
swmjupyter/form.html.jinja
swmjupyter/form.py
swmjupyter/job.sh.jinja
swmjupyter/spawner.py
swmjupyter-0.1.7.dist-info/LICENSE
swmjupyter-0.1.7.dist-info/METADATA
swmjupyter-0.1.7.dist-info/WHEEL
swmjupyter-0.1.7.dist-info/top_level.txt
swmjupyter-0.1.7.dist-info/RECORD
